pieoffice_gui/__init__.py
pieoffice_gui/__main__.py
pieoffice_gui/docs.py
pieoffice_gui/static/fonts/NotoMono-Regular.ttf
pieoffice_gui/static/fonts/NotoSansAnatolianHieroglyphs-Regular.ttf
pieoffice_gui/static/fonts/NotoSansArmenian-Regular.ttf
pieoffice_gui/static/fonts/NotoSansAvestan-Regular.ttf
pieoffice_gui/static/fonts/NotoSansCarian-Regular.ttf
pieoffice_gui/static/fonts/NotoSansCuneiform-Regular.ttf
pieoffice_gui/static/fonts/NotoSansCypriot-Regular.ttf
pieoffice_gui/static/fonts/NotoSansDevanagari-Regular.ttf
pieoffice_gui/static/fonts/NotoSansGothic-Regular.ttf
pieoffice_gui/static/fonts/NotoSansLinearB-Regular.ttf
pieoffice_gui/static/fonts/NotoSansLycian-Regular.ttf
pieoffice_gui/static/fonts/NotoSansLydian-Regular.ttf
pieoffice_gui/static/fonts/NotoSansOgham-Regular.ttf
pieoffice_gui/static/fonts/NotoSansOldItalic-Regular.ttf
pieoffice_gui/static/fonts/NotoSansOldPersian-Regular.ttf
pieoffice_gui-0.0.4.dist-info/LICENSE
pieoffice_gui-0.0.4.dist-info/METADATA
pieoffice_gui-0.0.4.dist-info/WHEEL
pieoffice_gui-0.0.4.dist-info/entry_points.txt
pieoffice_gui-0.0.4.dist-info/top_level.txt
pieoffice_gui-0.0.4.dist-info/RECORD
