Metadata-Version: 2.1
Name: pieoffice-gui
Version: 0.0.4
Summary: A GUI script converter for ancient (Proto-)Indo-European languages based on pieoffice.
Home-page: https://gitlab.com/caiogeraldes/pieoffice_gui
Author: Caio Geraldes
Author-email: caiogeraldes@protonmail.com
License: MIT
Platform: UNKNOWN
Classifier: Programming Language :: Python :: 3
Classifier: License :: OSI Approved :: MIT License
Classifier: Operating System :: OS Independent
Requires-Python: >=3.6
Requires-Dist: betacode
Requires-Dist: pieoffice
Requires-Dist: pygtrie
Requires-Dist: PySide2
